[
  {"title":"时尚，是一种态度！迪奥（Dior）烈艳蓝金唇膏口红3.5g（多色可选），经典热卖色，让你颠覆以往，绽放动人绝妙之美。绚丽色调，缔造闪亮唇妆，寻回法式优雅传统，尊贵配方，蕴含海茴香精华，柔滑丰盈美唇，同时令每一种唇膏色彩于双唇尽情闪耀。","imgurl":"img/goods1.jpg","price":"￥109","logo":"img/logo1.jpg","code":"abc1"},
  
  {"title":"韩国vidivici氨基酸女神泡沫洗面奶120ml","imgurl":"img/goods2.jpg","price":"￥588","code":"abc2"},
  
  {"title":"JMsolution水光蜂蜜补水面膜20片","imgurl":"img/goods3.jpg","price":"￥238","code":"abc3"},
  
  {"title":"【3盒】蒂佳婷药丸面膜（蓝色补水+绿色晒后修护+黑色","imgurl":"img/goods4.jpg","price":"￥768","code":"abc4"},
  
  {"title":"嫒柏莎 【仅限今日 抢79元2套】网红颜值法兰","imgurl":"img/goods5.jpg","price":"￥148","code":"abc5"},
  
  {"title":"AHC第3代玻尿酸精华液面膜5片","imgurl":"img/goods6.jpg","price":"￥118","code":"abc6"},
  
  {"title":"纤美媛. 【仅限今日 抢79元2套】加厚法兰绒颜值睡衣56色合集","imgurl":"img/goods7.jpg","price":"￥328","code":"abc7"}
]